{
  "driving_licence": {
    "parser_name": "DriverLicenseParser",
    "location": "us",
    "processor_id": "baf0cf598e3ddd6b"
  },
  "utility_bill": {
    "parser_name": "UtilityParser",
    "location": "us",
    "processor_id": "5be161d11102be84"
  },
  "pay_stub": {
    "parser_name": "PaySlipParser",
    "location": "us",
    "processor_id": "6e6ffde10d5c6566"
  },
  "unemployment_form": {
    "parser_name": "FormParser",
    "location": "us",
    "processor_id": "58d7348f7955db9c"
  },
  "claims_form": {
    "parser_name": "FormParser",
    "location": "us",
    "processor_id": "58d7348f7955db9c"
  }
}

